deepaipng/__init__.py
deepaipng/__main__.py
deepaipng/api.py
deepaipng-1.1.2.dist-info/LICENSE
deepaipng-1.1.2.dist-info/METADATA
deepaipng-1.1.2.dist-info/WHEEL
deepaipng-1.1.2.dist-info/RECORD
