Metadata-Version: 2.1
Name: deepaipng
Version: 1.1.2
Summary: Processes images with DeepAI and PIL by resizing, cropping to fit specified dimensions, making the background transparent
Home-page: https://github.com/DJStompZone/DeepAIPNG
License: ISC
Author: DJ Magar
Author-email: dj@deepai.org
Requires-Python: >=3.10
Classifier: License :: OSI Approved
Classifier: Programming Language :: Python :: 3
Classifier: Programming Language :: Python :: 3.10
Classifier: Programming Language :: Python :: 3.11
Classifier: Programming Language :: Python :: 3.12
Requires-Dist: httpx (>=0.27.0)
Requires-Dist: pillow (>=10.2.0,<11.0.0)
Requires-Dist: python-dotenv (>=1.0.1,<2.0.0)
Project-URL: Repository, https://github.com/DJStompZone/DeepAIPNG
